projects/your_project/rtl/scanner.v
`default_nettype none
`ifndef SCANNER_H
`define SCANNER_H
  module scanner(
    input wire       clk,
    output reg      hsync,
    output reg      vsync,
    output wire      display_on,
    output reg [9:0] abs_x,
    output reg [9:0] abs_y,
    input wire       reset
  );
    parameter H_DISPLAY = 640; // lượng pixel nhìn thấy được
    parameter H_LEFT_BOR = 48; // số pixel border bên trái
    parameter H_RIGHT_BOR = 16; // số pixel border bên phải
    parameter H_RETRACE = 96;  // xung nhịp cần 
  
    parameter V_DISPLAY = 480;
    parameter V_BOT_BOR = 10;
    parameter V_TOP_BOR = 33;
    parameter V_RETRACE = 2;
  
    
    parameter H_RETRACE_START = H_DISPLAY + H_RIGHT_BOR;
    parameter H_RETRACE_END = H_DISPLAY + H_RIGHT_BOR + H_RETRACE -1;
    parameter H_MAX = H_DISPLAY + H_RIGHT_BOR + H_LEFT_BOR + H_RETRACE - 1;
    parameter V_RETRACE_START = V_DISPLAY + V_BOT_BOR;
    parameter V_RETRACE_END = V_DISPLAY + V_BOT_BOR + V_RETRACE -1;
    parameter V_MAX = V_DISPLAY + V_BOT_BOR + V_TOP_BOR + V_RETRACE - 1;
  
    wire hmax = (abs_x == H_MAX) || reset;
    wire vmax = (abs_y == V_MAX) || reset;
  
    always @(posedge clk) begin
      hsync <= ~(abs_x >= H_RETRACE_START && abs_x <= H_RETRACE_END);
      if(hmax) abs_x <= 0; else abs_x <= abs_x + 1;
    end
    //lỗi ở đây
    always @(posedge clk) begin
      vsync <= ~(abs_y >= V_RETRACE_START && abs_y <= V_RETRACE_END);
      if(hmax) begin
        if(vmax) abs_y <= 0; else abs_y <= abs_y + 1;
      end
    end
  
    assign display_on = (abs_x < H_DISPLAY) && (abs_y < V_DISPLAY);
  endmodule
`endif

projects/your_project/tb/tb_scanner.v
//bước 1: dựng file, bao dây dẫn
`timescale 1ns / 1ps // đơn vị gốc 1ns, độ phân giải 1ps

module tb_scanner;
    // 1. dây input (phải dùng reg)
    reg clk;
    reg reset;

    // 2. dây output (dùng wire)
    wire hsync;
    wire vsync;
    wire display_on;
    wire [9:0] abs_x;
    wire [9:0] abs_y;


//bước 2: thêm module cần test
    scanner uut(
        .clk(clk),
        .reset(reset),
        .hsync(hsync),
        .vsync(vsync),
        .display_on(display_on),
        .abs_x(abs_x),
        .abs_y(abs_y)
    );


// bước 3: tạo thạch anh ảo
    always #20 clk = ~clk;


// bước 4: tạo kịch bản test
    initial begin
        $dumpfile("sim/scanner.vcd");
        $dumpvars(0, tb_scanner);

        clk = 0;
        reset = 1;

        #100
        reset = 0;

        #100000;

        $finish;
    end


// bước 5: đặt print giám sát
    always @(posedge clk) begin
        if(abs_x == 0 && abs_y > 0 && abs_y < 5) begin
            $display("Time: %0t ns | Quet xong hang ngang. abs_y dang o dong: %d", $time, abs_y);
        end
    end

endmodule

projects/your_project/sim/scanner.vcd
$date
	Tue Jun 23 09:24:12 2026
$end
$version
	Icarus Verilog
$end
$timescale
	1ps
$end
$scope module tb_scanner $end
$var wire 1 ! vsync $end
$var wire 1 " hsync $end
$var wire 1 # display_on $end
$var wire 10 $ abs_y [9:0] $end
$var wire 10 % abs_x [9:0] $end
$var reg 1 & clk $end
$var reg 1 ' reset $end
$scope module uut $end
$var wire 1 & clk $end
$var wire 1 # display_on $end
$var wire 1 ( hmax $end
$var wire 1 ' reset $end
$var wire 1 ) vmax $end
$var parameter 32 * H_DISPLAY $end
$var parameter 32 + H_LEFT_BOR $end
$var parameter 36 , H_MAX $end
$var parameter 32 - H_RETRACE $end
$var parameter 35 . H_RETRACE_END $end
$var parameter 33 / H_RETRACE_START $end
$var parameter 32 0 H_RIGHT_BOR $end
$var parameter 32 1 V_BOT_BOR $end
$var parameter 32 2 V_DISPLAY $end
$var parameter 36 3 V_MAX $end
$var parameter 32 4 V_RETRACE $end
$var parameter 35 5 V_RETRACE_END $end
$var parameter 33 6 V_RETRACE_START $end
$var parameter 32 7 V_TOP_BOR $end
$var reg 10 8 abs_x [9:0] $end
$var reg 10 9 abs_y [9:0] $end
$var reg 1 " hsync $end
$var reg 1 ! vsync $end
$upscope $end
$upscope $end
$enddefinitions $end
$comment Show the parameter values. $end
$dumpall
b100001 7
b111101010 6
b111101011 5
b10 4
b1000001100 3
b111100000 2
b1010 1
b10000 0
b1010010000 /
b1011101111 .
b1100000 -
b1100011111 ,
b110000 +
b1010000000 *
$end
#0
$dumpvars
bx 9
bx 8
1)
1(
1'
0&
bx %
bx $
x#
x"
x!
$end
#20000
1#
b0 %
b0 8
b0 $
b0 9
1&
#40000
0&
#60000
1!
1"
1&
#80000
0&
#100000
b1 %
b1 8
0(
0)
1&
0'
#120000
0&
#140000
b10 %
b10 8
1&
#160000
0&
#180000
b11 %
b11 8
1&
#200000
0&
#220000
b100 %
b100 8
1&
#240000
0&
#260000
b101 %
b101 8
1&
#280000
0&
#300000
b110 %
b110 8
1&
#320000
0&
#340000
b111 %
b111 8
1&
#360000
0&
#380000
b1000 %
b1000 8
1&
#400000
0&
#420000
b1001 %
b1001 8
1&
#440000
0&
#460000
b1010 %
b1010 8
1&
#480000
0&
#500000
b1011 %
b1011 8
1&
#520000
0&
#540000
b1100 %
b1100 8
1&
#560000
0&
#580000
b1101 %
b1101 8
1&
#600000
0&
#620000
b1110 %
b1110 8
1&
#640000
0&
#660000
b1111 %
b1111 8
1&
#680000
0&
#700000
b10000 %
b10000 8
1&
#720000
0&
#740000
b10001 %
b10001 8
1&
#760000
0&
#780000
b10010 %
b10010 8
1&
#800000
0&
#820000
b10011 %
b10011 8
1&
#840000
0&
#860000
b10100 %
b10100 8
1&
#880000
0&
#900000
b10101 %
b10101 8
1&
#920000
0&
#940000
b10110 %
b10110 8
1&
#960000
0&
#980000
b10111 %
b10111 8
1&
#1000000
0&
#1020000
b11000 %
b11000 8
1&
#1040000
0&
#1060000
b11001 %
b11001 8
1&
#1080000
0&
#1100000
b11010 %
b11010 8
1&
#1120000
0&
#1140000
b11011 %
b11011 8
1&
#1160000
0&
#1180000
b11100 %
b11100 8
1&
#1200000
0&
#1220000
b11101 %
b11101 8
1&
#1240000
0&
#1260000
b11110 %
b11110 8
1&
#1280000
0&
#1300000
b11111 %
b11111 8
1&
#1320000
0&
#1340000
b100000 %
b100000 8
1&
#1360000
0&
#1380000
b100001 %
b100001 8
1&
#1400000
0&
#1420000
b100010 %
b100010 8
1&
#1440000
0&
#1460000
b100011 %
b100011 8
1&
#1480000
0&
#1500000
b100100 %
b100100 8
1&
#1520000
0&
#1540000
b100101 %
b100101 8
1&
#1560000
0&
#1580000
b100110 %
b100110 8
1&
#1600000
0&
#1620000
b100111 %
b100111 8
1&
#1640000
0&
#1660000
b101000 %
b101000 8
1&
#1680000
0&
#1700000
b101001 %
b101001 8
1&
#1720000
0&
#1740000
b101010 %
b101010 8
1&
#1760000
0&
#1780000
b101011 %
b101011 8
1&
#1800000
0&
#1820000
b101100 %
b101100 8
1&
#1840000
0&
#1860000
b101101 %
b101101 8
1&
#1880000
0&
#1900000
b101110 %
b101110 8
1&
#1920000
0&
#1940000
b101111 %
b101111 8
1&
#1960000
0&
#1980000
b110000 %
b110000 8
1&
#2000000
0&
#2020000
b110001 %
b110001 8
1&
#2040000
0&
#2060000
b110010 %
b110010 8
1&
#2080000
0&
#2100000
b110011 %
b110011 8
1&
#2120000
0&
#2140000
b110100 %
b110100 8
1&
#2160000
0&
#2180000
b110101 %
b110101 8
1&
#2200000
0&
#2220000
b110110 %
b110110 8
1&
#2240000
0&
#2260000
b110111 %
b110111 8
1&
#2280000
0&
#2300000
b111000 %
b111000 8
1&
#2320000
0&
#2340000
b111001 %
b111001 8
1&
#2360000
0&
#2380000
b111010 %
b111010 8
1&
#2400000
0&
#2420000
b111011 %
b111011 8
1&
#2440000
0&
#2460000
b111100 %
b111100 8
1&
#2480000
0&
#2500000
b111101 %
b111101 8
1&
#2520000
0&
#2540000
b111110 %
b111110 8
1&
#2560000
0&
#2580000
b111111 %
b111111 8
1&
#2600000
0&
#2620000
b1000000 %
b1000000 8
1&
#2640000
0&
#2660000
b1000001 %
b1000001 8
1&
#2680000
0&
#2700000
b1000010 %
b1000010 8
1&
#2720000
0&
#2740000
b1000011 %
b1000011 8
1&
#2760000
0&
#2780000
b1000100 %
b1000100 8
1&
#2800000
0&
#2820000
b1000101 %
b1000101 8
1&
#2840000
0&
#2860000
b1000110 %
b1000110 8
1&
#2880000
0&
#2900000
b1000111 %
b1000111 8
1&
#2920000
0&
#2940000
b1001000 %
b1001000 8
1&
#2960000
0&
#2980000
b1001001 %
b1001001 8
1&
#3000000
0&
#3020000
b1001010 %
b1001010 8
1&
#3040000
0&
#3060000
b1001011 %
b1001011 8
1&
#3080000
0&
#3100000
b1001100 %
b1001100 8
1&
#3120000
0&
#3140000
b1001101 %
b1001101 8
1&
#3160000
0&
#3180000
b1001110 %
b1001110 8
1&
#3200000
0&
#3220000
b1001111 %
b1001111 8
1&
#3240000
0&
#3260000
b1010000 %
b1010000 8
1&
#3280000
0&
#3300000
b1010001 %
b1010001 8
1&
#3320000
0&
#3340000
b1010010 %
b1010010 8
1&
#3360000
0&
#3380000
b1010011 %
b1010011 8
1&
#3400000
0&
#3420000
b1010100 %
b1010100 8
1&
#3440000
0&
#3460000
b1010101 %
b1010101 8
1&
#3480000
0&
#3500000
b1010110 %
b1010110 8
1&
#3520000
0&
#3540000
b1010111 %
b1010111 8
1&
#3560000
0&
#3580000
b1011000 %
b1011000 8
1&
#3600000
0&
#3620000
b1011001 %
b1011001 8
1&
#3640000
0&
#3660000
b1011010 %
b1011010 8
1&
#3680000
0&
#3700000
b1011011 %
b1011011 8
1&
#3720000
0&
#3740000
b1011100 %
b1011100 8
1&
#3760000
0&
#3780000
b1011101 %
b1011101 8
1&
#3800000
0&
#3820000
b1011110 %
b1011110 8
1&
#3840000
0&
#3860000
b1011111 %
b1011111 8
1&
#3880000
0&
#3900000
b1100000 %
b1100000 8
1&
#3920000
0&
#3940000
b1100001 %
b1100001 8
1&
#3960000
0&
#3980000
b1100010 %
b1100010 8
1&
#4000000
0&
#4020000
b1100011 %
b1100011 8
1&
#4040000
0&
#4060000
b1100100 %
b1100100 8
1&
#4080000
0&
#4100000
b1100101 %
b1100101 8
1&
#4120000
0&
#4140000
b1100110 %
b1100110 8
1&
#4160000
0&
#4180000
b1100111 %
b1100111 8
1&
#4200000
0&
#4220000
b1101000 %
b1101000 8
1&
#4240000
0&
#4260000
b1101001 %
b1101001 8
1&
#4280000
0&
#4300000
b1101010 %
b1101010 8
1&
#4320000
0&
#4340000
b1101011 %
b1101011 8
1&
#4360000
0&
#4380000
b1101100 %
b1101100 8
1&
#4400000
0&
#4420000
b1101101 %
b1101101 8
1&
#4440000
0&
#4460000
b1101110 %
b1101110 8
1&
#4480000
0&
#4500000
b1101111 %
b1101111 8
1&
#4520000
0&
#4540000
b1110000 %
b1110000 8
1&
#4560000
0&
#4580000
b1110001 %
b1110001 8
1&
#4600000
0&
#4620000
b1110010 %
b1110010 8
1&
#4640000
0&
#4660000
b1110011 %
b1110011 8
1&
#4680000
0&
#4700000
b1110100 %
b1110100 8
1&
#4720000
0&
#4740000
b1110101 %
b1110101 8
1&
#4760000
0&
#4780000
b1110110 %
b1110110 8
1&
#4800000
0&
#4820000
b1110111 %
b1110111 8
1&
#4840000
0&
#4860000
b1111000 %
b1111000 8
1&
#4880000
0&
#4900000
b1111001 %
b1111001 8
1&
#4920000
0&
#4940000
b1111010 %
b1111010 8
1&
#4960000
0&
#4980000
b1111011 %
b1111011 8
1&
#5000000
0&
#5020000
b1111100 %
b1111100 8
1&
#5040000
0&
#5060000
b1111101 %
b1111101 8
1&
#5080000
0&
#5100000
b1111110 %
b1111110 8
1&
#5120000
0&
#5140000
b1111111 %
b1111111 8
1&
#5160000
0&
#5180000
b10000000 %
b10000000 8
1&
#5200000
0&
#5220000
b10000001 %
b10000001 8
1&
#5240000
0&
#5260000
b10000010 %
b10000010 8
1&
#5280000
0&
#5300000
b10000011 %
b10000011 8
1&
#5320000
0&
#5340000
b10000100 %
b10000100 8
1&
#5360000
0&
#5380000
b10000101 %
b10000101 8
1&
#5400000
0&
#5420000
b10000110 %
b10000110 8
1&
#5440000
0&
#5460000
b10000111 %
b10000111 8
1&
#5480000
0&
#5500000
b10001000 %
b10001000 8
1&
#5520000
0&
#5540000
b10001001 %
b10001001 8
1&
#5560000
0&
#5580000
b10001010 %
b10001010 8
1&
#5600000
0&
#5620000
b10001011 %
b10001011 8
1&
#5640000
0&
#5660000
b10001100 %
b10001100 8
1&
#5680000
0&
#5700000
b10001101 %
b10001101 8
1&
#5720000
0&
#5740000
b10001110 %
b10001110 8
1&
#5760000
0&
#5780000
b10001111 %
b10001111 8
1&
#5800000
0&
#5820000
b10010000 %
b10010000 8
1&
#5840000
0&
#5860000
b10010001 %
b10010001 8
1&
#5880000
0&
#5900000
b10010010 %
b10010010 8
1&
#5920000
0&
#5940000
b10010011 %
b10010011 8
1&
#5960000
0&
#5980000
b10010100 %
b10010100 8
1&
#6000000
0&
#6020000
b10010101 %
b10010101 8
1&
#6040000
0&
#6060000
b10010110 %
b10010110 8
1&
#6080000
0&
#6100000
b10010111 %
b10010111 8
1&
#6120000
0&
#6140000
b10011000 %
b10011000 8
1&
#6160000
0&
#6180000
b10011001 %
b10011001 8
1&
#6200000
0&
#6220000
b10011010 %
b10011010 8
1&
#6240000
0&
#6260000
b10011011 %
b10011011 8
1&
#6280000
0&
#6300000
b10011100 %
b10011100 8
1&
#6320000
0&
#6340000
b10011101 %
b10011101 8
1&
#6360000
0&
#6380000
b10011110 %
b10011110 8
1&
#6400000
0&
#6420000
b10011111 %
b10011111 8
1&
#6440000
0&
#6460000
b10100000 %
b10100000 8
1&
#6480000
0&
#6500000
b10100001 %
b10100001 8
1&
#6520000
0&
#6540000
b10100010 %
b10100010 8
1&
#6560000
0&
#6580000
b10100011 %
b10100011 8
1&
#6600000
0&
#6620000
b10100100 %
b10100100 8
1&
#6640000
0&
#6660000
b10100101 %
b10100101 8
1&
#6680000
0&
#6700000
b10100110 %
b10100110 8
1&
#6720000
0&
#6740000
b10100111 %
b10100111 8
1&
#6760000
0&
#6780000
b10101000 %
b10101000 8
1&
#6800000
0&
#6820000
b10101001 %
b10101001 8
1&
#6840000
0&
#6860000
b10101010 %
b10101010 8
1&
#6880000
0&
#6900000
b10101011 %
b10101011 8
1&
#6920000
0&
#6940000
b10101100 %
b10101100 8
1&
#6960000
0&
#6980000
b10101101 %
b10101101 8
1&
#7000000
0&
#7020000
b10101110 %
b10101110 8
1&
#7040000
0&
#7060000
b10101111 %
b10101111 8
1&
#7080000
0&
#7100000
b10110000 %
b10110000 8
1&
#7120000
0&
#7140000
b10110001 %
b10110001 8
1&
#7160000
0&
#7180000
b10110010 %
b10110010 8
1&
#7200000
0&
#7220000
b10110011 %
b10110011 8
1&
#7240000
0&
#7260000
b10110100 %
b10110100 8
1&
#7280000
0&
#7300000
b10110101 %
b10110101 8
1&
#7320000
0&
#7340000
b10110110 %
b10110110 8
1&
#7360000
0&
#7380000
b10110111 %
b10110111 8
1&
#7400000
0&
#7420000
b10111000 %
b10111000 8
1&
#7440000
0&
#7460000
b10111001 %
b10111001 8
1&
#7480000
0&
#7500000
b10111010 %
b10111010 8
1&
#7520000
0&
#7540000
b10111011 %
b10111011 8
1&
#7560000
0&
#7580000
b10111100 %
b10111100 8
1&
#7600000
0&
#7620000
b10111101 %
b10111101 8
1&
#7640000
0&
#7660000
b10111110 %
b10111110 8
1&
#7680000
0&
#7700000
b10111111 %
b10111111 8
1&
#7720000
0&
#7740000
b11000000 %
b11000000 8
1&
#7760000
0&
#7780000
b11000001 %
b11000001 8
1&
#7800000
0&
#7820000
b11000010 %
b11000010 8
1&
#7840000
0&
#7860000
b11000011 %
b11000011 8
1&
#7880000
0&
#7900000
b11000100 %
b11000100 8
1&
#7920000
0&
#7940000
b11000101 %
b11000101 8
1&
#7960000
0&
#7980000
b11000110 %
b11000110 8
1&
#8000000
0&
#8020000
b11000111 %
b11000111 8
1&
#8040000
0&
#8060000
b11001000 %
b11001000 8
1&
#8080000
0&
#8100000
b11001001 %
b11001001 8
1&
#8120000
0&
#8140000
b11001010 %
b11001010 8
1&
#8160000
0&
#8180000
b11001011 %
b11001011 8
1&
#8200000
0&
#8220000
b11001100 %
b11001100 8
1&
#8240000
0&
#8260000
b11001101 %
b11001101 8
1&
#8280000
0&
#8300000
b11001110 %
b11001110 8
1&
#8320000
0&
#8340000
b11001111 %
b11001111 8
1&
#8360000
0&
#8380000
b11010000 %
b11010000 8
1&
#8400000
0&
#8420000
b11010001 %
b11010001 8
1&
#8440000
0&
#8460000
b11010010 %
b11010010 8
1&
#8480000
0&
#8500000
b11010011 %
b11010011 8
1&
#8520000
0&
#8540000
b11010100 %
b11010100 8
1&
#8560000
0&
#8580000
b11010101 %
b11010101 8
1&
#8600000
0&
#8620000
b11010110 %
b11010110 8
1&
#8640000
0&
#8660000
b11010111 %
b11010111 8
1&
#8680000
0&
#8700000
b11011000 %
b11011000 8
1&
#8720000
0&
#8740000
b11011001 %
b11011001 8
1&
#8760000
0&
#8780000
b11011010 %
b11011010 8
1&
#8800000
0&
#8820000
b11011011 %
b11011011 8
1&
#8840000
0&
#8860000
b11011100 %
b11011100 8
1&
#8880000
0&
#8900000
b11011101 %
b11011101 8
1&
#8920000
0&
#8940000
b11011110 %
b11011110 8
1&
#8960000
0&
#8980000
b11011111 %
b11011111 8
1&
#9000000
0&
#9020000
b11100000 %
b11100000 8
1&
#9040000
0&
#9060000
b11100001 %
b11100001 8
1&
#9080000
0&
#9100000
b11100010 %
b11100010 8
1&
#9120000
0&
#9140000
b11100011 %
b11100011 8
1&
#9160000
0&
#9180000
b11100100 %
b11100100 8
1&
#9200000
0&
#9220000
b11100101 %
b11100101 8
1&
#9240000
0&
#9260000
b11100110 %
b11100110 8
1&
#9280000
0&
#9300000
b11100111 %
b11100111 8
1&
#9320000
0&
#9340000
b11101000 %
b11101000 8
1&
#9360000
0&
#9380000
b11101001 %
b11101001 8
1&
#9400000
0&
#9420000
b11101010 %
b11101010 8
1&
#9440000
0&
#9460000
b11101011 %
b11101011 8
1&
#9480000
0&
#9500000
b11101100 %
b11101100 8
1&
#9520000
0&
#9540000
b11101101 %
b11101101 8
1&
#9560000
0&
#9580000
b11101110 %
b11101110 8
1&
#9600000
0&
#9620000
b11101111 %
b11101111 8
1&
#9640000
0&
#9660000
b11110000 %
b11110000 8
1&
#9680000
0&
#9700000
b11110001 %
b11110001 8
1&
#9720000
0&
#9740000
b11110010 %
b11110010 8
1&
#9760000
0&
#9780000
b11110011 %
b11110011 8
1&
#9800000
0&
#9820000
b11110100 %
b11110100 8
1&
#9840000
0&
#9860000
b11110101 %
b11110101 8
1&
#9880000
0&
#9900000
b11110110 %
b11110110 8
1&
#9920000
0&
#9940000
b11110111 %
b11110111 8
1&
#9960000
0&
#9980000
b11111000 %
b11111000 8
1&
#10000000
0&
#10020000
b11111001 %
b11111001 8
1&
#10040000
0&
#10060000
b11111010 %
b11111010 8
1&
#10080000
0&
#10100000
b11111011 %
b11111011 8
1&
#10120000
0&
#10140000
b11111100 %
b11111100 8
1&
#10160000
0&
#10180000
b11111101 %
b11111101 8
1&
#10200000
0&
#10220000
b11111110 %
b11111110 8
1&
#10240000
0&
#10260000
b11111111 %
b11111111 8
1&
#10280000
0&
#10300000
b100000000 %
b100000000 8
1&
#10320000
0&
#10340000
b100000001 %
b100000001 8
1&
#10360000
0&
#10380000
b100000010 %
b100000010 8
1&
#10400000
0&
#10420000
b100000011 %
b100000011 8
1&
#10440000
0&
#10460000
b100000100 %
b100000100 8
1&
#10480000
0&
#10500000
b100000101 %
b100000101 8
1&
#10520000
0&
#10540000
b100000110 %
b100000110 8
1&
#10560000
0&
#10580000
b100000111 %
b100000111 8
1&
#10600000
0&
#10620000
b100001000 %
b100001000 8
1&
#10640000
0&
#10660000
b100001001 %
b100001001 8
1&
#10680000
0&
#10700000
b100001010 %
b100001010 8
1&
#10720000
0&
#10740000
b100001011 %
b100001011 8
1&
#10760000
0&
#10780000
b100001100 %
b100001100 8
1&
#10800000
0&
#10820000
b100001101 %
b100001101 8
1&
#10840000
0&
#10860000
b100001110 %
b100001110 8
1&
#10880000
0&
#10900000
b100001111 %
b100001111 8
1&
#10920000
0&
#10940000
b100010000 %
b100010000 8
1&
#10960000
0&
#10980000
b100010001 %
b100010001 8
1&
#11000000
0&
#11020000
b100010010 %
b100010010 8
1&
#11040000
0&
#11060000
b100010011 %
b100010011 8
1&
#11080000
0&
#11100000
b100010100 %
b100010100 8
1&
#11120000
0&
#11140000
b100010101 %
b100010101 8
1&
#11160000
0&
#11180000
b100010110 %
b100010110 8
1&
#11200000
0&
#11220000
b100010111 %
b100010111 8
1&
#11240000
0&
#11260000
b100011000 %
b100011000 8
1&
#11280000
0&
#11300000
b100011001 %
b100011001 8
1&
#11320000
0&
#11340000
b100011010 %
b100011010 8
1&
#11360000
0&
#11380000
b100011011 %
b100011011 8
1&
#11400000
0&
#11420000
b100011100 %
b100011100 8
1&
#11440000
0&
#11460000
b100011101 %
b100011101 8
1&
#11480000
0&
#11500000
b100011110 %
b100011110 8
1&
#11520000
0&
#11540000
b100011111 %
b100011111 8
1&
#11560000
0&
#11580000
b100100000 %
b100100000 8
1&
#11600000
0&
#11620000
b100100001 %
b100100001 8
1&
#11640000
0&
#11660000
b100100010 %
b100100010 8
1&
#11680000
0&
#11700000
b100100011 %
b100100011 8
1&
#11720000
0&
#11740000
b100100100 %
b100100100 8
1&
#11760000
0&
#11780000
b100100101 %
b100100101 8
1&
#11800000
0&
#11820000
b100100110 %
b100100110 8
1&
#11840000
0&
#11860000
b100100111 %
b100100111 8
1&
#11880000
0&
#11900000
b100101000 %
b100101000 8
1&
#11920000
0&
#11940000
b100101001 %
b100101001 8
1&
#11960000
0&
#11980000
b100101010 %
b100101010 8
1&
#12000000
0&
#12020000
b100101011 %
b100101011 8
1&
#12040000
0&
#12060000
b100101100 %
b100101100 8
1&
#12080000
0&
#12100000
b100101101 %
b100101101 8
1&
#12120000
0&
#12140000
b100101110 %
b100101110 8
1&
#12160000
0&
#12180000
b100101111 %
b100101111 8
1&
#12200000
0&
#12220000
b100110000 %
b100110000 8
1&
#12240000
0&
#12260000
b100110001 %
b100110001 8
1&
#12280000
0&
#12300000
b100110010 %
b100110010 8
1&
#12320000
0&
#12340000
b100110011 %
b100110011 8
1&
#12360000
0&
#12380000
b100110100 %
b100110100 8
1&
#12400000
0&
#12420000
b100110101 %
b100110101 8
1&
#12440000
0&
#12460000
b100110110 %
b100110110 8
1&
#12480000
0&
#12500000
b100110111 %
b100110111 8
1&
#12520000
0&
#12540000
b100111000 %
b100111000 8
1&
#12560000
0&
#12580000
b100111001 %
b100111001 8
1&
#12600000
0&
#12620000
b100111010 %
b100111010 8
1&
#12640000
0&
#12660000
b100111011 %
b100111011 8
1&
#12680000
0&
#12700000
b100111100 %
b100111100 8
1&
#12720000
0&
#12740000
b100111101 %
b100111101 8
1&
#12760000
0&
#12780000
b100111110 %
b100111110 8
1&
#12800000
0&
#12820000
b100111111 %
b100111111 8
1&
#12840000
0&
#12860000
b101000000 %
b101000000 8
1&
#12880000
0&
#12900000
b101000001 %
b101000001 8
1&
#12920000
0&
#12940000
b101000010 %
b101000010 8
1&
#12960000
0&
#12980000
b101000011 %
b101000011 8
1&
#13000000
0&
#13020000
b101000100 %
b101000100 8
1&
#13040000
0&
#13060000
b101000101 %
b101000101 8
1&
#13080000
0&
#13100000
b101000110 %
b101000110 8
1&
#13120000
0&
#13140000
b101000111 %
b101000111 8
1&
#13160000
0&
#13180000
b101001000 %
b101001000 8
1&
#13200000
0&
#13220000
b101001001 %
b101001001 8
1&
#13240000
0&
#13260000
b101001010 %
b101001010 8
1&
#13280000
0&
#13300000
b101001011 %
b101001011 8
1&
#13320000
0&
#13340000
b101001100 %
b101001100 8
1&
#13360000
0&
#13380000
b101001101 %
b101001101 8
1&
#13400000
0&
#13420000
b101001110 %
b101001110 8
1&
#13440000
0&
#13460000
b101001111 %
b101001111 8
1&
#13480000
0&
#13500000
b101010000 %
b101010000 8
1&
#13520000
0&
#13540000
b101010001 %
b101010001 8
1&
#13560000
0&
#13580000
b101010010 %
b101010010 8
1&
#13600000
0&
#13620000
b101010011 %
b101010011 8
1&
#13640000
0&
#13660000
b101010100 %
b101010100 8
1&
#13680000
0&
#13700000
b101010101 %
b101010101 8
1&
#13720000
0&
#13740000
b101010110 %
b101010110 8
1&
#13760000
0&
#13780000
b101010111 %
b101010111 8
1&
#13800000
0&
#13820000
b101011000 %
b101011000 8
1&
#13840000
0&
#13860000
b101011001 %
b101011001 8
1&
#13880000
0&
#13900000
b101011010 %
b101011010 8
1&
#13920000
0&
#13940000
b101011011 %
b101011011 8
1&
#13960000
0&
#13980000
b101011100 %
b101011100 8
1&
#14000000
0&
#14020000
b101011101 %
b101011101 8
1&
#14040000
0&
#14060000
b101011110 %
b101011110 8
1&
#14080000
0&
#14100000
b101011111 %
b101011111 8
1&
#14120000
0&
#14140000
b101100000 %
b101100000 8
1&
#14160000
0&
#14180000
b101100001 %
b101100001 8
1&
#14200000
0&
#14220000
b101100010 %
b101100010 8
1&
#14240000
0&
#14260000
b101100011 %
b101100011 8
1&
#14280000
0&
#14300000
b101100100 %
b101100100 8
1&
#14320000
0&
#14340000
b101100101 %
b101100101 8
1&
#14360000
0&
#14380000
b101100110 %
b101100110 8
1&
#14400000
0&
#14420000
b101100111 %
b101100111 8
1&
#14440000
0&
#14460000
b101101000 %
b101101000 8
1&
#14480000
0&
#14500000
b101101001 %
b101101001 8
1&
#14520000
0&
#14540000
b101101010 %
b101101010 8
1&
#14560000
0&
#14580000
b101101011 %
b101101011 8
1&
#14600000
0&
#14620000
b101101100 %
b101101100 8
1&
#14640000
0&
#14660000
b101101101 %
b101101101 8
1&
#14680000
0&
#14700000
b101101110 %
b101101110 8
1&
#14720000
0&
#14740000
b101101111 %
b101101111 8
1&
#14760000
0&
#14780000
b101110000 %
b101110000 8
1&
#14800000
0&
#14820000
b101110001 %
b101110001 8
1&
#14840000
0&
#14860000
b101110010 %
b101110010 8
1&
#14880000
0&
#14900000
b101110011 %
b101110011 8
1&
#14920000
0&
#14940000
b101110100 %
b101110100 8
1&
#14960000
0&
#14980000
b101110101 %
b101110101 8
1&
#15000000
0&
#15020000
b101110110 %
b101110110 8
1&
#15040000
0&
#15060000
b101110111 %
b101110111 8
1&
#15080000
0&
#15100000
b101111000 %
b101111000 8
1&
#15120000
0&
#15140000
b101111001 %
b101111001 8
1&
#15160000
0&
#15180000
b101111010 %
b101111010 8
1&
#15200000
0&
#15220000
b101111011 %
b101111011 8
1&
#15240000
0&
#15260000
b101111100 %
b101111100 8
1&
#15280000
0&
#15300000
b101111101 %
b101111101 8
1&
#15320000
0&
#15340000
b101111110 %
b101111110 8
1&
#15360000
0&
#15380000
b101111111 %
b101111111 8
1&
#15400000
0&
#15420000
b110000000 %
b110000000 8
1&
#15440000
0&
#15460000
b110000001 %
b110000001 8
1&
#15480000
0&
#15500000
b110000010 %
b110000010 8
1&
#15520000
0&
#15540000
b110000011 %
b110000011 8
1&
#15560000
0&
#15580000
b110000100 %
b110000100 8
1&
#15600000
0&
#15620000
b110000101 %
b110000101 8
1&
#15640000
0&
#15660000
b110000110 %
b110000110 8
1&
#15680000
0&
#15700000
b110000111 %
b110000111 8
1&
#15720000
0&
#15740000
b110001000 %
b110001000 8
1&
#15760000
0&
#15780000
b110001001 %
b110001001 8
1&
#15800000
0&
#15820000
b110001010 %
b110001010 8
1&
#15840000
0&
#15860000
b110001011 %
b110001011 8
1&
#15880000
0&
#15900000
b110001100 %
b110001100 8
1&
#15920000
0&
#15940000
b110001101 %
b110001101 8
1&
#15960000
0&
#15980000
b110001110 %
b110001110 8
1&
#16000000
0&
#16020000
b110001111 %
b110001111 8
1&
#16040000
0&
#16060000
b110010000 %
b110010000 8
1&
#16080000
0&
#16100000
b110010001 %
b110010001 8
1&
#16120000
0&
#16140000
b110010010 %
b110010010 8
1&
#16160000
0&
#16180000
b110010011 %
b110010011 8
1&
#16200000
0&
#16220000
b110010100 %
b110010100 8
1&
#16240000
0&
#16260000
b110010101 %
b110010101 8
1&
#16280000
0&
#16300000
b110010110 %
b110010110 8
1&
#16320000
0&
#16340000
b110010111 %
b110010111 8
1&
#16360000
0&
#16380000
b110011000 %
b110011000 8
1&
#16400000
0&
#16420000
b110011001 %
b110011001 8
1&
#16440000
0&
#16460000
b110011010 %
b110011010 8
1&
#16480000
0&
#16500000
b110011011 %
b110011011 8
1&
#16520000
0&
#16540000
b110011100 %
b110011100 8
1&
#16560000
0&
#16580000
b110011101 %
b110011101 8
1&
#16600000
0&
#16620000
b110011110 %
b110011110 8
1&
#16640000
0&
#16660000
b110011111 %
b110011111 8
1&
#16680000
0&
#16700000
b110100000 %
b110100000 8
1&
#16720000
0&
#16740000
b110100001 %
b110100001 8
1&
#16760000
0&
#16780000
b110100010 %
b110100010 8
1&
#16800000
0&
#16820000
b110100011 %
b110100011 8
1&
#16840000
0&
#16860000
b110100100 %
b110100100 8
1&
#16880000
0&
#16900000
b110100101 %
b110100101 8
1&
#16920000
0&
#16940000
b110100110 %
b110100110 8
1&
#16960000
0&
#16980000
b110100111 %
b110100111 8
1&
#17000000
0&
#17020000
b110101000 %
b110101000 8
1&
#17040000
0&
#17060000
b110101001 %
b110101001 8
1&
#17080000
0&
#17100000
b110101010 %
b110101010 8
1&
#17120000
0&
#17140000
b110101011 %
b110101011 8
1&
#17160000
0&
#17180000
b110101100 %
b110101100 8
1&
#17200000
0&
