projects/your_project/rtl/cactus_sprite.v
module cactus_sprite(
  input wire [4:0] x, 
  input wire [4:0] y,
  output reg pixel
);
  reg [7:0] mem[79:0];
initial begin
    mem[0] = 8'hc0;     mem[1] = 8'h00;     mem[2] = 8'h00;     mem[3] = 8'h00;
    mem[4] = 8'he0;     mem[5] = 8'h01;     mem[6] = 8'h00;     mem[7] = 8'h00;
    mem[8] = 8'he0;     mem[9] = 8'h01;     mem[10] = 8'h00;     mem[11] = 8'h00;
    mem[12] = 8'he0;     mem[13] = 8'h01;     mem[14] = 8'h00;     mem[15] = 8'h00;
    mem[16] = 8'he6;     mem[17] = 8'h11;     mem[18] = 8'h00;     mem[19] = 8'h00;
    mem[20] = 8'hef;     mem[21] = 8'h39;     mem[22] = 8'h00;     mem[23] = 8'h00;
    mem[24] = 8'hef;     mem[25] = 8'h39;     mem[26] = 8'h00;     mem[27] = 8'h00;
    mem[28] = 8'hef;     mem[29] = 8'h39;     mem[30] = 8'h00;     mem[31] = 8'h00;
    mem[32] = 8'hff;     mem[33] = 8'h39;     mem[34] = 8'h00;     mem[35] = 8'h00;
    mem[36] = 8'hff;     mem[37] = 8'h39;     mem[38] = 8'h00;     mem[39] = 8'h00;
    mem[40] = 8'hfe;     mem[41] = 8'h39;     mem[42] = 8'h00;     mem[43] = 8'h00;
    mem[44] = 8'hfc;     mem[45] = 8'h39;     mem[46] = 8'h00;     mem[47] = 8'h00;
    mem[48] = 8'he0;     mem[49] = 8'h3f;     mem[50] = 8'h00;     mem[51] = 8'h00;
    mem[52] = 8'he0;     mem[53] = 8'h1f;     mem[54] = 8'h00;     mem[55] = 8'h00;
    mem[56] = 8'he0;     mem[57] = 8'h0f;     mem[58] = 8'h00;     mem[59] = 8'h00;
    mem[60] = 8'he0;     mem[61] = 8'h01;     mem[62] = 8'h00;     mem[63] = 8'h00;
    mem[64] = 8'he0;     mem[65] = 8'h01;     mem[66] = 8'h00;     mem[67] = 8'h00;
    mem[68] = 8'he0;     mem[69] = 8'h01;     mem[70] = 8'h00;     mem[71] = 8'h00;
    mem[72] = 8'he0;     mem[73] = 8'h01;     mem[74] = 8'h00;     mem[75] = 8'h00;
    mem[76] = 8'he0;     mem[77] = 8'h01;     mem[78] = 8'h00;     mem[79] = 8'h00;
  end
  wire [6:0] addr = {y[4:0],x[4:3]};
  assign pixel = mem[addr][x[2:0]];
endmodule

projects/your_project/rtl/c_cactus.v
`default_nettype none

module c_cactus(
  input wire clk,
  input wire [9:0] abs_x,
  input wire [9:0] abs_y,
  output wire draw_cactus,
  input wire game_over,
  input wire rst_n
);
    
  // --- Cài đặt Kích thước và Tọa độ ---
  parameter GROUND_Y = 420; 
  parameter ZOOM = 2;
  // Cài đặt Xương rồng (Cactus)
  parameter CAC_W = 20 * ZOOM;
  parameter CAC_H = 20 * ZOOM;
  parameter CAC_START_X = 640; // Xuất phát từ mép phải màn hình
  parameter CAC_SPEED = 6;     // Tốc độ chạy của xương rồng
  wire [9:0] cac_y = GROUND_Y - CAC_H;
  // ==========================================
  // 1. THANH GHI TRẠNG THÁI (STATE REGISTERS)
  // ==========================================
  reg [9:0] cac_x = CAC_START_X;

  // ==========================================
  // 4. GAME ENGINE CHÍNH (VẬT LÝ & DI CHUYỂN)
  // ==========================================
  wire frame_tick = (abs_x == 0) & (abs_y == 0);
  always @(posedge clk) begin
      if (~rst_n) begin
          cac_x      <= CAC_START_X;
      end else if (frame_tick) begin
          if (game_over) begin
          end else begin
                // ---- XỬ LÝ XƯƠNG RỒNG CHẠY ----
                if (cac_x <= CAC_SPEED) 
                    cac_x <= CAC_START_X; // Cuốn chiếu vòng lại
                else 
                    cac_x <= cac_x - CAC_SPEED;
          end
      end
  end

  // ==========================================
  // 5. MẠCH RENDER ĐỒ HỌA
  // ==========================================
  wire [9:0] local_cac_x = abs_x - cac_x;
  wire [9:0] local_cac_y = abs_y - cac_y;
  wire cac_pixel_on;

  cactus_sprite my_cactus(
    .x(local_cac_x[5:1]),
    .y(local_cac_y[5:1]),
    .pixel(cac_pixel_on)
  );
                     
  assign draw_cactus = (abs_x >= cac_x) && (abs_x < cac_x + CAC_W) &&
                     (abs_y >= cac_y) && (abs_y < cac_y + CAC_H) &&
                     cac_pixel_on;
                     

endmodule

projects/your_project/tb/tb_cactus.v
`timescale 10ns/1ns

module tb_cactus;
    reg clk;
    reg [9:0] abs_x;
    reg [9:0] abs_y;
    reg game_over;
    reg rst_n;
    wire draw_cactus;
    reg [9:0] prev_x;
    integer x,y;

    c_cactus cactus_inst(
        .clk(clk),
        .abs_x(abs_x),
        .abs_y(abs_y),
        .rst_n(rst_n),
        .game_over(game_over),
        .draw_cactus(draw_cactus)
    );
    
    always #2 clk = ~clk;
    initial begin : VONG_LAP_X_QUANG
        $dumpfile("tb_cactus.vcd");
        $dumpvars(0, cactus_inst.cac_x);
        $dumpvars(0, cactus_inst.cac_y);
        $dumpvars(0, cactus_inst.frame_tick);
        $dumpvars(0, rst_n);
        $dumpvars(0, game_over);
        $dumpvars(0, draw_cactus);

        clk = 0;
        abs_x = 0;
        abs_y = 0;
        game_over = 0;
        rst_n = 0;

        #10;
        
        rst_n = 1;


        $display("Time %0t ns | === START ===", $time);
        
        for(y = 0; y < 40; y = y + 1) begin
            abs_y = y + cactus_inst.cac_y;
            for (x = 0; x < 40; x = x + 1) begin
                abs_x = x + cactus_inst.cac_x;
                @(posedge clk);
                if (draw_cactus) $write("█");
                else $write(" ");
            end
            $write("\n");
        end
        $display("\nTime %0t ns | ==============================", $time);
        $display("Time %0t ns | === HOAN THANH TEST SPRITE ===", $time);

        while (cactus_inst.cac_x > 400) begin
            force cactus_inst.frame_tick = 1;
            @(posedge clk);
            force cactus_inst.frame_tick = 0;
            repeat(2) @(posedge clk);
        end
        $display("Time %0t ns | === HOAN THANH TEST CHUYEN DONG ===", $time);

        while (cactus_inst.cac_x < 500 ) begin
            force cactus_inst.frame_tick = 1;
            @(posedge clk);
            force cactus_inst.frame_tick = 0;
            repeat(2) @(posedge clk);
        end
        $display("Time %0t ns | === HOAN THANH TEST QUAY VE ===", $time);

        while (cactus_inst.cac_x > 600 ) begin
            force cactus_inst.frame_tick = 1;
            @(posedge clk);
            force cactus_inst.frame_tick = 0;
            repeat(2) @(posedge clk);
        end

        rst_n = 0;
        while (cactus_inst.cac_x != 640 ) begin
            force cactus_inst.frame_tick = 1;
            @(posedge clk);
            force cactus_inst.frame_tick = 0;
            rst_n = 0;
            repeat(2) @(posedge clk);
        end
        $display("Time %0t ns | === HOAN THANH TEST RESET ===", $time);

        game_over = 1;
        while (cactus_inst.cac_x - prev_x != 0) begin
            force cactus_inst.frame_tick = 1;
            @(posedge clk);
            force cactus_inst.frame_tick = 0;
            game_over = 0;
            prev_x = cactus_inst.cac_x;
            repeat(2) @(posedge clk);
        end
        $display("Time %0t ns | === HOAN THANH TEST GAMEOVER ===", $time);
        $finish;
    end

endmodule

projects/your_project/sim/tb_cactus.vcd
$date
	Fri Jun 26 10:08:47 2026
$end
$version
	Icarus Verilog
$end
$timescale
	1ns
$end
$scope module tb_cactus $end
$scope module cactus_inst $end
$var reg 10 ! cac_x [9:0] $end
$upscope $end
$upscope $end
$scope module tb_cactus $end
$scope module cactus_inst $end
$var wire 10 " cac_y [9:0] $end
$upscope $end
$upscope $end
$scope module tb_cactus $end
$scope module cactus_inst $end
$var wire 1 # frame_tick $end
$upscope $end
$upscope $end
$scope module tb_cactus $end
$var reg 1 $ rst_n $end
$upscope $end
$scope module tb_cactus $end
$var reg 1 % game_over $end
$upscope $end
$scope module tb_cactus $end
$var wire 1 & draw_cactus $end
$upscope $end
$enddefinitions $end
$comment Show the parameter values. $end
$dumpall
$end
#0
$dumpvars
0&
0%
0$
z#
b101111100 "
b1010000000 !
$end
#100
1$
#540
1&
#700
0&
#2140
1&
#2300
0&
#3660
1&
#3980
0&
#5260
1&
#5580
0&
#6860
1&
#7180
0&
#8460
1&
#8780
0&
#10060
1&
#10380
0&
#11660
1&
#11980
0&
#12940
1&
#13100
0&
#13260
1&
#13580
0&
#13820
1&
#13900
0&
#14540
1&
#14700
0&
#14860
1&
#15180
0&
#15420
1&
#15500
0&
#16060
1&
#16380
0&
#16460
1&
#16780
0&
#16940
1&
#17180
0&
#17660
1&
#17980
0&
#18060
1&
#18380
0&
#18540
1&
#18780
0&
#19260
1&
#19580
0&
#19660
1&
#19980
0&
#20140
1&
#20380
0&
#20860
1&
#21180
0&
#21260
1&
#21580
0&
#21740
1&
#21980
0&
#22460
1&
#22780
0&
#22860
1&
#23180
0&
#23340
1&
#23580
0&
#24060
1&
#24380
0&
#24460
1&
#24780
0&
#24940
1&
#25180
0&
#25660
1&
#26380
0&
#26540
1&
#26780
0&
#27260
1&
#27980
0&
#28140
1&
#28380
0&
#28860
1&
#29580
0&
#29740
1&
#29980
0&
#30460
1&
#31180
0&
#31340
1&
#31580
0&
#32140
1&
#32780
0&
#32940
1&
#33180
0&
#33740
1&
#34380
0&
#34540
1&
#34780
0&
#35420
1&
#35980
0&
#36140
1&
#36380
0&
#37020
1&
#37580
0&
#37740
1&
#37980
0&
#38860
1&
#39580
0&
#40460
1&
#41180
0&
#42060
1&
#42700
0&
#43660
1&
#44300
0&
#45260
1&
#45820
0&
#46860
1&
#47420
0&
#48460
1&
#48780
0&
#50060
1&
#50380
0&
#51660
1&
#51980
0&
#53260
1&
#53580
0&
#54860
1&
#55180
0&
#56460
1&
#56780
0&
#58060
1&
#58380
0&
#59660
1&
#59980
0&
#61260
1&
#61580
0&
#62860
1&
#63180
0&
#64060
1#
#64100
0#
#64180
b1001111010 !
1#
#64220
b1001110100 !
0#
#64300
1#
#64340
0#
#64420
b1001101110 !
1#
#64460
b1001101000 !
0#
#64540
1#
#64580
0#
#64660
b1001100010 !
1#
#64700
b1001011100 !
0#
#64780
1#
#64820
0#
#64900
b1001010110 !
1#
#64940
b1001010000 !
0#
#65020
1#
#65060
0#
#65140
b1001001010 !
1#
#65180
b1001000100 !
0#
#65260
1#
#65300
0#
#65380
b1000111110 !
1#
#65420
b1000111000 !
0#
#65500
1#
#65540
0#
#65620
b1000110010 !
1#
#65660
b1000101100 !
0#
#65740
1#
#65780
0#
#65860
b1000100110 !
1#
#65900
b1000100000 !
0#
#65980
1#
#66020
0#
#66100
b1000011010 !
1#
#66140
b1000010100 !
0#
#66220
1#
#66260
0#
#66340
b1000001110 !
1#
#66380
b1000001000 !
0#
#66460
1#
#66500
0#
#66580
b1000000010 !
1#
#66620
b111111100 !
0#
#66700
1#
#66740
0#
#66820
b111110110 !
1#
#66860
b111110000 !
0#
#66940
1#
#66980
0#
#67060
b111101010 !
1#
#67100
b111100100 !
0#
#67180
1#
#67220
0#
#67300
b111011110 !
1#
#67340
b111011000 !
0#
#67420
1#
#67460
0#
#67540
b111010010 !
1#
#67580
b111001100 !
0#
#67660
1#
#67700
0#
#67780
b111000110 !
1#
#67820
b111000000 !
0#
#67900
1#
#67940
0#
#68020
b110111010 !
1#
#68060
b110110100 !
0#
#68140
1#
#68180
0#
#68260
b110101110 !
1#
#68300
b110101000 !
0#
#68380
1#
#68420
0#
#68500
b110100010 !
1#
#68540
b110011100 !
0#
#68620
1#
#68660
0#
#68740
b110010110 !
1#
#68780
b110010000 !
0#
#68860
1#
#68900
0#
#68980
b110001010 !
1#
#69020
b110000100 !
0#
#69100
1#
#69140
0#
#69220
b101111110 !
1#
#69260
b101111000 !
0#
#69340
1#
#69380
0#
#69460
b101110010 !
1#
#69500
b101101100 !
0#
#69580
1#
#69620
0#
#69700
b101100110 !
1#
#69740
b101100000 !
0#
#69820
1#
#69860
0#
#69940
b101011010 !
1#
#69980
b101010100 !
0#
#70060
1#
#70100
0#
#70180
b101001110 !
1#
#70220
b101001000 !
0#
#70300
1#
#70340
0#
#70420
b101000010 !
1#
#70460
b100111100 !
0#
#70540
1#
#70580
0#
#70660
b100110110 !
1#
#70700
b100110000 !
0#
#70780
1#
#70820
0#
#70900
b100101010 !
1#
#70940
b100100100 !
0#
#71020
1#
#71060
0#
#71140
b100011110 !
1#
#71180
b100011000 !
0#
#71260
1#
#71300
0#
#71380
b100010010 !
1#
#71420
b100001100 !
0#
#71500
1#
#71540
0#
#71620
b100000110 !
1#
#71660
b100000000 !
0#
#71740
1#
#71780
0#
#71860
b11111010 !
1#
#71900
b11110100 !
0#
#71980
1#
#72020
0#
#72100
b11101110 !
1#
#72140
b11101000 !
0#
#72220
1#
#72260
0#
#72340
b11100010 !
1#
#72380
b11011100 !
0#
#72460
1#
#72500
0#
#72580
b11010110 !
1#
#72620
b11010000 !
0#
#72700
1#
#72740
0#
#72820
b11001010 !
1#
#72860
b11000100 !
0#
#72940
1#
#72980
0#
#73060
b10111110 !
1#
#73100
b10111000 !
0#
#73180
1#
#73220
0#
#73300
b10110010 !
1#
#73340
b10101100 !
0#
#73420
1#
#73460
0#
#73540
b10100110 !
1#
#73580
b10100000 !
0#
#73660
1#
#73700
0#
#73780
b10011010 !
1#
#73820
b10010100 !
0#
#73900
1#
#73940
0#
#74020
b10001110 !
1#
#74060
b10001000 !
0#
#74140
1#
#74180
0#
#74260
b10000010 !
1#
#74300
b1111100 !
0#
#74380
1#
#74420
0#
#74500
b1110110 !
1#
#74540
b1110000 !
0#
#74620
1#
#74660
0#
#74740
b1101010 !
1#
#74780
b1100100 !
0#
#74860
1#
#74900
0#
#74980
b1011110 !
1#
#75020
b1011000 !
0#
#75100
1#
#75140
0#
#75220
b1010010 !
1#
#75260
b1001100 !
0#
#75340
1#
#75380
0#
#75460
b1000110 !
1#
#75500
b1000000 !
0#
#75580
1#
#75620
0#
#75700
b111010 !
1#
#75740
b110100 !
0#
#75820
1#
#75860
0#
#75940
b101110 !
1#
#75980
b101000 !
0#
#76060
1#
#76100
0#
#76180
b100010 !
1#
#76220
b11100 !
0#
#76300
1#
#76340
0#
#76420
b10110 !
1#
#76460
b10000 !
0#
#76540
1#
#76580
0#
#76660
b1010 !
1#
#76700
b100 !
0#
#76780
1#
#76820
0#
#76900
b1010000000 !
1#
#76940
b1001111010 !
0#
#77020
1#
#77060
0#
#77140
b1001110100 !
1#
#77180
b1001101110 !
0#
#77260
1#
#77300
0#
#77380
b1001101000 !
1#
#77420
b1001100010 !
0#
#77500
1#
#77540
0#
#77620
b1001011100 !
1#
#77660
b1001010110 !
0#
#77740
1#
0$
#77780
b1010000000 !
0#
#77860
1%
