projects/your_project/rtl/dino_sprite.v
`default_nettype none

module dino_sprite (
    input wire [4:0] x, // Tọa độ local X (0 -> 19)
    input wire [4:0] y, // Tọa độ local Y (0 -> 19)
    output wire pixel,
    input wire sprite
);
  // Lưới 32x20 = 80 byte. Lưu ý: Lấy LSB làm pixel bên trái trước.
  reg [7:0] mem[159:0];

 initial begin
  //sprite 0
    mem[0] = 8'h00;     mem[1] = 8'hfc;     mem[2] = 8'h07;     mem[3] = 8'h00;
    mem[4] = 8'h00;     mem[5] = 8'hf6;     mem[6] = 8'h0f;     mem[7] = 8'h00;
    mem[8] = 8'h00;     mem[9] = 8'hfe;     mem[10] = 8'h0f;     mem[11] = 8'h00;
    mem[12] = 8'h00;     mem[13] = 8'hfe;     mem[14] = 8'h0f;     mem[15] = 8'h00;
    mem[16] = 8'h00;     mem[17] = 8'hfe;     mem[18] = 8'h0f;     mem[19] = 8'h00;
    mem[20] = 8'h00;     mem[21] = 8'h7e;     mem[22] = 8'h00;     mem[23] = 8'h00;
    mem[24] = 8'h00;     mem[25] = 8'hfe;     mem[26] = 8'h03;     mem[27] = 8'h00;
    mem[28] = 8'h00;     mem[29] = 8'h3e;     mem[30] = 8'h00;     mem[31] = 8'h00;
    mem[32] = 8'h01;     mem[33] = 8'h3f;     mem[34] = 8'h00;     mem[35] = 8'h00;
    mem[36] = 8'h81;     mem[37] = 8'hff;     mem[38] = 8'h00;     mem[39] = 8'h00;
    mem[40] = 8'hc3;     mem[41] = 8'hbf;     mem[42] = 8'h00;     mem[43] = 8'h00;
    mem[44] = 8'he7;     mem[45] = 8'h3f;     mem[46] = 8'h00;     mem[47] = 8'h00;
    mem[48] = 8'hff;     mem[49] = 8'h3f;     mem[50] = 8'h00;     mem[51] = 8'h00;
    mem[52] = 8'hfe;     mem[53] = 8'h1f;     mem[54] = 8'h00;     mem[55] = 8'h00;
    mem[56] = 8'hfc;     mem[57] = 8'h0f;     mem[58] = 8'h00;     mem[59] = 8'h00;
    mem[60] = 8'hf8;     mem[61] = 8'h07;     mem[62] = 8'h00;     mem[63] = 8'h00;
    mem[64] = 8'he0;     mem[65] = 8'h0e;     mem[66] = 8'h00;     mem[67] = 8'h00;
    mem[68] = 8'h60;     mem[69] = 8'h00;     mem[70] = 8'h00;     mem[71] = 8'h00;
    mem[72] = 8'h20;     mem[73] = 8'h00;     mem[74] = 8'h00;     mem[75] = 8'h00;
    mem[76] = 8'h60;     mem[77] = 8'h00;     mem[78] = 8'h00;     mem[79] = 8'h00;
    //sprite 1
    mem[128] = 8'h00;     mem[129] = 8'hfc;     mem[130] = 8'h07;     mem[131] = 8'h00;
    mem[132] = 8'h00;     mem[133] = 8'hf6;     mem[134] = 8'h0f;     mem[135] = 8'h00;
    mem[136] = 8'h00;     mem[137] = 8'hfe;     mem[138] = 8'h0f;     mem[139] = 8'h00;
    mem[140] = 8'h00;     mem[141] = 8'hfe;     mem[142] = 8'h0f;     mem[143] = 8'h00;
    mem[144] = 8'h00;     mem[145] = 8'hfe;     mem[146] = 8'h0f;     mem[147] = 8'h00;
    mem[148] = 8'h00;     mem[149] = 8'h7e;     mem[150] = 8'h00;     mem[151] = 8'h00;
    mem[152] = 8'h00;     mem[153] = 8'hfe;     mem[154] = 8'h03;     mem[155] = 8'h00;
    mem[156] = 8'h00;     mem[157] = 8'h3e;     mem[158] = 8'h00;     mem[159] = 8'h00;
    mem[160] = 8'h01;     mem[161] = 8'h3f;     mem[162] = 8'h00;     mem[163] = 8'h00;
    mem[164] = 8'h81;     mem[165] = 8'hff;     mem[166] = 8'h00;     mem[167] = 8'h00;
    mem[168] = 8'hc3;     mem[169] = 8'hbf;     mem[170] = 8'h00;     mem[171] = 8'h00;
    mem[172] = 8'he7;     mem[173] = 8'h3f;     mem[174] = 8'h00;     mem[175] = 8'h00;
    mem[176] = 8'hff;     mem[177] = 8'h3f;     mem[178] = 8'h00;     mem[179] = 8'h00;
    mem[180] = 8'hfe;     mem[181] = 8'h1f;     mem[182] = 8'h00;     mem[183] = 8'h00;
    mem[184] = 8'hfc;     mem[185] = 8'h0f;     mem[186] = 8'h00;     mem[187] = 8'h00;
    mem[188] = 8'hf8;     mem[189] = 8'h07;     mem[190] = 8'h00;     mem[191] = 8'h00;
    mem[192] = 8'h20;     mem[193] = 8'h06;     mem[194] = 8'h00;     mem[195] = 8'h00;
    mem[196] = 8'h60;     mem[197] = 8'h04;     mem[198] = 8'h00;     mem[199] = 8'h00;
    mem[200] = 8'h00;     mem[201] = 8'h04;     mem[202] = 8'h00;     mem[203] = 8'h00;
    mem[204] = 8'h00;     mem[205] = 8'h0c;     mem[206] = 8'h00;     mem[207] = 8'h00;
  end

  // Dùng lại tuyệt chiêu toán học: Địa chỉ = y * 4 + x / 8
  wire [7:0] addr = {sprite, y[4:0], x[4:3]};
  assign pixel = mem[addr][x[2:0]];

endmodule

projects/your_project/rtl/c_dino.v
`default_nettype none
`define COLOR_CYAN  3'd5

module c_dino #(

    parameter GROUND_Y = 420; 
    parameter DINO_SIZE = 20; 
    parameter ZOOM = 2;
    parameter DINO_X = 60;  
)
(
    input wire clk,
    input wire frame_tick,
    input wire [9:0] abs_x,
    input wire [9:0] abs_y,
    input wire       rst_n,
    input wire       game_over,
    output wire      draw_dino,
    output reg       state,
    input wire       command
);

    

    // Cài đặt Khủng long (Dino)

    parameter DINO_W = DINO_SIZE * ZOOM; // 80 pixel
    parameter DINO_H = DINO_SIZE * ZOOM; // 80 pixel
    localparam DINO_START_Y = GROUND_Y - DINO_H; // 320 - 80 = 240


    // ==========================================
    // 1. THANH GHI TRẠNG THÁI (STATE REGISTERS)
    // ==========================================
    reg signed [10:0] dino_y_reg = DINO_START_Y;
    reg signed [10:0] dino_vy = 0;

    // ==========================================
    // 3. GAME ENGINE CHÍNH (VẬT LÝ & DI CHUYỂN)
    // ==========================================
    always @(posedge clk) begin
        if (~rst_n) begin
            dino_y_reg <= DINO_START_Y;
            dino_vy    <= 0;
            state <= 0;
        end else if (frame_tick) begin
          if (game_over) begin
          end else begin
              // ---- XỬ LÝ KHỦNG LONG NHẢY ----
              if (dino_y_reg < DINO_START_Y) begin
                  dino_y_reg <= dino_y_reg + dino_vy;
                  dino_vy    <= dino_vy + 1; // Trọng lực
              end else begin
                  dino_y_reg <= DINO_START_Y;
                  state <= 0;
                  if (command) begin
                      dino_vy    <= -12; // Lực bật nhảy
                      dino_y_reg <= DINO_START_Y - 12; 
                      state <= 1;
                  end else begin
                      dino_vy    <= 0;
                  end
              end
            end
        end
    end

    wire [9:0] dino_y = dino_y_reg[9:0];

    // ==========================================
    // 5. MẠCH RENDER ĐỒ HỌA
    // ==========================================
    wire [9:0] local_dino_x = abs_x - DINO_X;
    wire [9:0] local_dino_y = abs_y - dino_y;
    wire dino_pixel_on;

    dino_sprite my_dino (
      .x(local_dino_x[5:1]), 
      .y(local_dino_y[5:1]),
      .pixel(dino_pixel_on)
    );

    assign draw_dino  = (abs_x >= DINO_X) && (abs_x < DINO_X + DINO_W) &&
                       (abs_y >= dino_y) && (abs_y < dino_y + DINO_H) &&
                       dino_pixel_on;

endmodule

projects/your_project/tb/tb_dino.v
`timescale 10ns/10ns

module tb_dino;
    reg clk;
    reg rst_n;
    reg game_over;
    reg command;
    reg [9:0] abs_x;
    reg [9:0] abs_y;
    reg [9:0] prev_y;
    wire draw_dino;
    wire state;
    integer x,y;

    c_dino dino_i (
        .clk(clk),
        .abs_x(abs_x),
        .abs_y(abs_y),
        .rst_n(rst_n),
        .game_over(game_over),
        .draw_dino(draw_dino),
        .state(state),
        .command(command)
    );

    always #2 clk = ~clk;
    
    task pump_frametick;
        begin 
            force dino_i.frame_tick = 1;
            @(posedge clk);
            force dino_i.frame_tick = 0;
            @(posedge clk);
        end
    endtask

    initial begin : TEST
        $dumpfile("tb_dino.vcd");
        $dumpvars(0, rst_n);
        $dumpvars(0, game_over);
        $dumpvars(0, state);
        $dumpvars(0, command);
        $dumpvars(0, dino_i.dino_y_reg);
        $dumpvars(0, dino_i.dino_y_reg);

        clk = 0;
        rst_n = 0;
        game_over = 0;
        command = 0;
        abs_x = 0;
        abs_y = 0;
        
        #4; 
        rst_n = 1;
        $display("Time %0t ns | === START ===", $time);

        #4;
        for(y = 0; y < 40; y = y + 1) begin
            abs_y = dino_i.DINO_START_Y + y;
            for(x = 0; x < 40; x = x + 1) begin
                abs_x = dino_i.DINO_X + x;
                @(posedge clk);
                if(draw_dino) $write("█");
                else $write(" ");
            end
            $write("\n");
        end
        $display("Time %0t ns | === HOAN THANH TEST SPRITE ===", $time);

        #4;
        prev_y = dino_i.DINO_START_Y;
        command = 1;
        repeat(5) pump_frametick();
        command = 0;
        repeat(5) pump_frametick();
        if (dino_i.dino_y_reg == prev_y) $display("Time %0t ns | === TEST JUMP FAIL ===", $time);
        else $display("Time %0t ns | === TEST JUMP OK===", $time);
        if (state == 0) $display("Time %0t ns | === TEST STATE FAIL ===", $time);
        else $display("Time %0t ns | === TEST STATE OK ===", $time);


        repeat(30) pump_frametick();
        if (dino_i.dino_y_reg != dino_i.DINO_START_Y) $display("Time %0t ns | === TEST FALL FAIL===", $time);
        else $display("Time %0t ns | === TEST FALL OK===", $time);
        if (state == 0) $display("Time %0t ns | === TEST STATE OK ===", $time);
        else $display("Time %0t ns | === TEST STATE FAIL ===", $time);

        #4;
        command = 1;
        pump_frametick();
        command = 0;
        rst_n = 0;
        pump_frametick();
        rst_n = 1;
        #4;
        if (dino_i.dino_y_reg != dino_i.DINO_START_Y) $display("Time %0t ns | === TEST RESET FAIL===", $time);
        else $display("Time %0t ns | === TEST RESET OK===", $time);

        #4;
        command = 1;
        pump_frametick();
        command = 0;
        pump_frametick();
        game_over = 1;
        @(posedge clk);
        prev_y = dino_i.dino_y_reg;
        repeat(2) pump_frametick();
        if (prev_y == dino_i.dino_y_reg) $display("Time %0t ns | === TEST GAMEOVER OK ===", $time);
        else $display("Time %0t ns | === TEST GAMEOVER FAIL ===", $time);

        $display("Time %0t ns | === HOAN THANH TEST ===", $time);
        $finish;

    end
endmodule

projects/your_project/sim/tb_dino.vcd
$date
	Thu Jun 25 14:13:49 2026
$end
$version
	Icarus Verilog
$end
$timescale
	10ns
$end
$scope module tb_dino $end
$var reg 1 ! rst_n $end
$upscope $end
$scope module tb_dino $end
$var reg 1 " game_over $end
$upscope $end
$scope module tb_dino $end
$var wire 1 # state $end
$upscope $end
$scope module tb_dino $end
$var reg 1 $ command $end
$upscope $end
$scope module tb_dino $end
$scope module dino_i $end
$var reg 11 % dino_y_reg [10:0] $end
$upscope $end
$upscope $end
$enddefinitions $end
$comment Show the parameter values. $end
$dumpall
$end
#0
$dumpvars
b101111100 %
0$
x#
0"
0!
$end
#2
0#
#4
1!
#6412
1$
#6414
1#
b101110000 %
#6422
b101100100 %
#6430
b101011001 %
#6438
b101001111 %
#6446
b101000110 %
#6450
0$
#6454
b100111110 %
#6462
b100110111 %
#6470
b100110001 %
#6478
b100101100 %
#6486
b100101000 %
#6494
b100100101 %
#6502
b100100011 %
#6510
b100100010 %
#6526
b100100011 %
#6534
b100100101 %
#6542
b100101000 %
#6550
b100101100 %
#6558
b100110001 %
#6566
b100110111 %
#6574
b100111110 %
#6582
b101000110 %
#6590
b101001111 %
#6598
b101011001 %
#6606
b101100100 %
#6614
b101110000 %
#6622
b101111101 %
#6630
0#
b101111100 %
#6734
1#
b101110000 %
1$
#6738
0!
0$
#6742
0#
b101111100 %
#6746
1!
#6754
1#
b101110000 %
1$
#6758
0$
#6762
b101100100 %
#6766
1"
